<?xml version="1.0" encoding="utf-8"?>
<databaseChangeLog
    xmlns="http://www.liquibase.org/xml/ns/dbchangelog"
    xmlns:ext="http://www.liquibase.org/xml/ns/dbchangelog-ext"
    xmlns:xsi="http://www.w3.org/2001/XMLSchema-instance"
    xsi:schemaLocation="http://www.liquibase.org/xml/ns/dbchangelog http://www.liquibase.org/xml/ns/dbchangelog/dbchangelog-3.5.xsd
                        http://www.liquibase.org/xml/ns/dbchangelog-ext http://www.liquibase.org/xml/ns/dbchangelog/dbchangelog-ext.xsd">

    <property name="now" value="now()" dbms="h2"/>

    <property name="now" value="now()" dbms="mysql"/>
    <property name="autoIncrement" value="true"/>

    <property name="floatType" value="float4" dbms="postgresql, h2"/>
    <property name="floatType" value="float" dbms="mysql, oracle, mssql"/>

    <!--
        Added the entity Organization.
    -->
    <changeSet id="20180626033606-1" author="jhipster">
        <createTable tableName="tbl_organizations">
            <column name="id" type="bigint" autoIncrement="${autoIncrement}">
                <constraints primaryKey="true" nullable="false"/>
            </column>
            <column name="jhi_type" type="varchar(255)">
                <constraints nullable="true" />
            </column>

            <column name="name" type="varchar(255)">
                <constraints nullable="true" />
            </column>

            <column name="latitude" type="${floatType}">
                <constraints nullable="true" />
            </column>

            <column name="longitude" type="${floatType}">
                <constraints nullable="true" />
            </column>

            <column name="created_by" type="varchar(255)">
                <constraints nullable="true" />
            </column>

            <column name="created_on" type="timestamp">
                <constraints nullable="true" />
            </column>

            <column name="last_updated_by" type="varchar(255)">
                <constraints nullable="true" />
            </column>

            <column name="last_updated_on" type="timestamp">
                <constraints nullable="true" />
            </column>

            <column name="description" type="varchar(255)">
                <constraints nullable="true" />
            </column>

            <column name="contact_1" type="varchar(255)">
                <constraints nullable="true" />
            </column>

            <column name="contact_1_value" type="varchar(255)">
                <constraints nullable="true" />
            </column>

            <column name="contact_2" type="varchar(255)">
                <constraints nullable="true" />
            </column>

            <column name="contact_2_value" type="varchar(255)">
                <constraints nullable="true" />
            </column>

            <column name="contact_3" type="varchar(255)">
                <constraints nullable="true" />
            </column>

            <column name="contact_3_value" type="varchar(255)">
                <constraints nullable="true" />
            </column>

            <column name="content_status" type="varchar(255)">
                <constraints nullable="true" />
            </column>

            <column name="uuid" type="varchar(255)">
                <constraints nullable="true" />
            </column>

            <!-- jhipster-needle-liquibase-add-column - JHipster will add columns here, do not remove-->
        </createTable>
        <dropDefaultValue tableName="tbl_organizations" columnName="created_on" columnDataType="datetime"/>
        <dropDefaultValue tableName="tbl_organizations" columnName="last_updated_on" columnDataType="datetime"/>

    </changeSet>
    <changeSet author="user" id="20180710070621">
        <addColumn tableName="tbl_organizations">
            <column name="location_id" type="bigint">
                <constraints nullable="true"/>
            </column>
        </addColumn>
    </changeSet>
    <!-- jhipster-needle-liquibase-add-changeset - JHipster will add changesets here, do not remove-->
</databaseChangeLog>
